{
    "key": "group_635960195a3f1",
    "title": "(Block) Savings Calculator",
    "fields": [
        {
            "key": "field_639bb0bcd1548",
            "label": "Anchor Tags",
            "name": "anchor_tags",
            "aria-label": "",
            "type": "clone",
            "instructions": "",
            "required": 0,
            "conditional_logic": 0,
            "wrapper": {
                "width": "",
                "class": "",
                "id": ""
            },
            "clone": [
                "group_63754ef8cd652"
            ],
            "display": "seamless",
            "layout": "",
            "prefix_label": 0,
            "prefix_name": 0
        },
        {
            "key": "field_639bb0bbd1547",
            "label": "Padding",
            "name": "paddings",
            "aria-label": "",
            "type": "clone",
            "instructions": "",
            "required": 0,
            "conditional_logic": 0,
            "wrapper": {
                "width": "",
                "class": "",
                "id": ""
            },
            "clone": [
                "group_6306b010a5e67"
            ],
            "display": "seamless",
            "layout": "",
            "prefix_label": 0,
            "prefix_name": 0
        },
        {
            "key": "field_63596019596f8",
            "label": "Savings Calculator Form ID",
            "name": "form_id",
            "aria-label": "",
            "type": "number",
            "instructions": "Enter the gravity form ID for the savings calculator.",
            "required": 1,
            "conditional_logic": 0,
            "wrapper": {
                "width": "",
                "class": "",
                "id": ""
            },
            "default_value": "",
            "min": "",
            "max": "",
            "placeholder": "",
            "step": "",
            "prepend": "",
            "append": ""
        }
    ],
    "location": [
        [
            {
                "param": "block",
                "operator": "==",
                "value": "acf\/savings-calculator"
            }
        ]
    ],
    "menu_order": 0,
    "position": "normal",
    "style": "default",
    "label_placement": "top",
    "instruction_placement": "label",
    "hide_on_screen": "",
    "active": true,
    "description": "",
    "show_in_rest": 0,
    "modified": 1671147923
}